[
  {
    "id": 1,
    "seatNumber": 1,
    "seatRow": 1,
    "hallId": 1
  },
  {
    "id": 2,
    "seatNumber": 2,
    "seatRow": 1,
    "hallId": 1
  },
  {
    "id": 3,
    "seatNumber": 3,
    "seatRow": 1,
    "hallId": 1
  },
  {
    "id": 4,
    "seatNumber": 1,
    "seatRow": 2,
    "hallId": 1
  },
  {
    "id": 5,
    "seatNumber": 2,
    "seatRow": 2,
    "hallId": 1
  },
  {
    "id": 6,
    "seatNumber": 1,
    "seatRow": 1,
    "hallId": 2
  },
  {
    "id": 7,
    "seatNumber": 2,
    "seatRow": 1,
    "hallId": 2
  },
  {
    "id": 8,
    "seatNumber": 1,
    "seatRow": 2,
    "hallId": 2
  }
]